Metadata-Version: 1.1
Name: johnnyLibrary
Version: 0.0.7
Summary: Personal library with needed functions
Home-page: UNKNOWN
Author: Jan Kołodziej
Author-email: jankolodziej04@gmail.com
License: MIT
Keywords: personal
Platform: UNKNOWN
Classifier: Development Status :: 5 - Production/Stable
Classifier: Intended Audience :: Education
Classifier: Operating System :: Microsoft :: Windows :: Windows 10
Classifier: License :: OSI Approved :: MIT License
Classifier: Programming Language :: Python :: 3
